adminalerts/__init__.py
adminalerts/admin.py
adminalerts/apps.py
adminalerts/forms.py
adminalerts/models.py
adminalerts/plugins.py
adminalerts/rules.py
adminalerts/urls.py
adminalerts/views.py
adminalerts/views_ajax.py
adminalerts/migrations/0001_initial.py
adminalerts/migrations/0002_adminalert_user.py
adminalerts/migrations/0003_auto_20180802_1558.py
adminalerts/migrations/0004_rename_uuid.py
adminalerts/migrations/0005_update_uuid.py
adminalerts/migrations/0006_adminalert_require_auth.py
adminalerts/migrations/__init__.py
adminalerts/templates/adminalerts/adminalert_confirm_delete.html
adminalerts/templates/adminalerts/adminalert_form.html
adminalerts/templates/adminalerts/alert_detail.html
adminalerts/templates/adminalerts/alert_list.html
adminalerts/tests/__init__.py
adminalerts/tests/test_models.py
adminalerts/tests/test_permissions.py
adminalerts/tests/test_permissions_ajax.py
adminalerts/tests/test_plugins.py
adminalerts/tests/test_ui.py
adminalerts/tests/test_views.py
adminalerts/tests/test_views_ajax.py
appalerts/__init__.py
appalerts/admin.py
appalerts/api.py
appalerts/apps.py
appalerts/models.py
appalerts/plugins.py
appalerts/rules.py
appalerts/urls.py
appalerts/views.py
appalerts/views_ajax.py
appalerts/migrations/0001_initial.py
appalerts/migrations/__init__.py
appalerts/static/appalerts/js/appalerts.js
appalerts/static/appalerts/js/appalerts_list.js
appalerts/templates/appalerts/alert_list.html
appalerts/tests/__init__.py
appalerts/tests/test_api.py
appalerts/tests/test_models.py
appalerts/tests/test_permissions.py
appalerts/tests/test_ui.py
appalerts/tests/test_views.py
bgjobs/__init__.py
bgjobs/admin.py
bgjobs/apps.py
bgjobs/models.py
bgjobs/plugins.py
bgjobs/rules.py
bgjobs/urls.py
bgjobs/views.py
bgjobs/migrations/0001_initial.py
bgjobs/migrations/0002_backgroundjoblogentry.py
bgjobs/migrations/0003_backgroundjob_date_created.py
bgjobs/migrations/0004_backgroundjob_user.py
bgjobs/migrations/0005_auto_20190128_1210.py
django_sodar_core-0.10.1.dist-info/AUTHORS.rst
django_sodar_core-0.10.1.dist-info/LICENSE
django_sodar_core-0.10.1.dist-info/METADATA
django_sodar_core-0.10.1.dist-info/WHEEL
django_sodar_core-0.10.1.dist-info/top_level.txt
django_sodar_core-0.10.1.dist-info/RECORD
