Metadata-Version: 2.1
Name: django-sodar-core
Version: 0.10.1
Summary: SODAR Core framework and project management apps
Home-page: https://github.com/bihealth/sodar-core
Author: Berlin Institute of Health, Core Unit Bioinformatics
Author-email: cubi@bihealth.de
License: UNKNOWN
Platform: UNKNOWN
Classifier: Framework :: Django
Classifier: Framework :: Django :: 3.2
Classifier: Intended Audience :: Developers
Classifier: License :: OSI Approved :: MIT License
Classifier: Natural Language :: English
Classifier: Operating System :: POSIX :: Linux
Classifier: Programming Language :: Python
Classifier: Programming Language :: Python :: 3
Classifier: Programming Language :: Python :: 3.7
Classifier: Programming Language :: Python :: 3.8
Classifier: Programming Language :: Python :: 3.9
Classifier: Topic :: Internet :: WWW/HTTP
Classifier: Topic :: Internet :: WWW/HTTP :: Dynamic Content
Requires-Python: >=3.7
Requires-Dist: django-environ (<0.5,>=0.4.5)
Requires-Dist: argon2-cffi (<20.2,>=20.1.0)
Requires-Dist: django-crispy-forms (<1.12,>=1.11.1)
Requires-Dist: mistune (<0.9,>=0.8.4)
Requires-Dist: django-docs (<0.4,>=0.3.1)
Requires-Dist: awesome-slugify (<1.7,>=1.6.5)
Requires-Dist: django (<3.3,>=3.2.1)
Requires-Dist: pytz (>=2021.1)
Requires-Dist: django-rest-knox (<4.2,>=4.1.0)
Requires-Dist: wheel (==0.36.2)
Requires-Dist: django-autocomplete-light (<3.9,>=3.8.2)
Requires-Dist: django-pagedown (<2.3,>=2.2.0)
Requires-Dist: django-markupfield (<2.1,>=2.0.0)
Requires-Dist: celery (<5.1,>=5.0.5)
Requires-Dist: django-saml2-auth-ai (<2.2,>=2.1.6)
Requires-Dist: psycopg2-binary (<2.9,>=2.8.6)
Requires-Dist: sphinx-rtd-theme (<0.6,>=0.5.1)
Requires-Dist: versioneer (>=0.19)
Requires-Dist: django-model-utils (<4.2,>=4.1.1)
Requires-Dist: django-db-file-storage (==0.5.5)
Requires-Dist: djangorestframework (<3.13,>=3.12.2)
Requires-Dist: Sphinx (<3.6,>=3.5.1)
Requires-Dist: django-iconify (==0.1.0.post1)
Requires-Dist: markdown (<3.4,>=3.3.4)
Requires-Dist: rules (<2.3,>=2.2)
